.gitignore
LICENSE.txt
MANIFEST.in
README.md
setup.cfg
setup.py
Djangle_CLI.egg-info/PKG-INFO
Djangle_CLI.egg-info/SOURCES.txt
Djangle_CLI.egg-info/dependency_links.txt
Djangle_CLI.egg-info/entry_points.txt
Djangle_CLI.egg-info/not-zip-safe
Djangle_CLI.egg-info/requires.txt
Djangle_CLI.egg-info/top_level.txt
djangle/__init__.py
djangle/cli/__init__.py
djangle/cli/commands/__init__.py
djangle/cli/commands/base_helper.py
djangle/cli/commands/creator/__init__.py
djangle/cli/commands/creator/main.py
djangle/cli/commands/creator/helper/__init__.py
djangle/cli/commands/creator/helper/create.py
djangle/cli/commands/creator/helper/identifier.py
djangle/cli/commands/destroyer/__init__.py
djangle/cli/commands/destroyer/main.py
djangle/cli/commands/destroyer/helpers/__init__.py
djangle/cli/commands/destroyer/helpers/base.py
djangle/cli/commands/generator/__init__.py
djangle/cli/commands/generator/main.py
djangle/cli/commands/generator/helpers/__init__.py
djangle/cli/commands/generator/helpers/admin.py
djangle/cli/commands/generator/helpers/base.py
djangle/cli/commands/generator/helpers/fields.json
djangle/cli/commands/generator/helpers/form.py
djangle/cli/commands/generator/helpers/model.py
djangle/cli/commands/generator/helpers/serializer.py
djangle/cli/commands/generator/helpers/template.py
djangle/cli/commands/generator/helpers/view.py
djangle/cli/commands/generator/helpers/viewset.py
djangle/cli/templates/__init__.py
djangle/cli/templates/admin.py
djangle/cli/templates/docker.py
djangle/cli/templates/form.py
djangle/cli/templates/model.py
djangle/cli/templates/pipfile.py
djangle/cli/templates/requirements.py
djangle/cli/templates/route.py
djangle/cli/templates/serializer.py
djangle/cli/templates/settings.py
djangle/cli/templates/template.py
djangle/cli/templates/urls.py
djangle/cli/templates/view.py
djangle/cli/templates/viewset.py
djangle/cli/templates/git_repo/__init__.py
djangle/cli/templates/git_repo/gitignore.py
djangle/cli/templates/git_repo/readme.py
tests/conftest.py
tests/creator/test_new_app.py
tests/creator/test_new_project.py
tests/destroyer/test_admin.py
tests/destroyer/test_form.py
tests/destroyer/test_model.py
tests/destroyer/test_resource.py
tests/destroyer/test_serializer.py
