Metadata-Version: 1.1
Name: Djangle-CLI
Version: 0.0.1
Summary: CLI for managing Django projects
Home-page: https://github.com/oleoneto/djangle
Author: Leo Neto
Author-email: leo@ekletik.com
License: BSD
Project-URL: Source Code, https://github.com/oleoneto/djangle/
Project-URL: Documentation, https://github.com/oleoneto/djangle/
Keywords: django automate cli command line tools rails ember python framework devops
Platform: UNKNOWN
Classifier: Environment :: Web Environment
Classifier: Framework :: Django
Classifier: Intended Audience :: Developers
Classifier: Operating System :: OS Independent
Classifier: Programming Language :: Python
Classifier: Programming Language :: Python :: 3
Classifier: Programming Language :: Python :: 3.6
Classifier: Programming Language :: Python :: 3.7
Classifier: Programming Language :: Python :: 3 :: Only
Classifier: Topic :: Software Development :: Libraries :: Application Frameworks
Classifier: Topic :: Software Development :: Libraries :: Python Modules
